<?xml version="1.0" encoding="UTF-8"?>
<objects serializationModel="Studio.02.01.00">
	<object class="AudioFile" id="{3af3fe6c-6e2c-4ce9-98e7-e7937e8343cc}">
		<property name="assetPath">
			<value>SX_Collision_Water_2.wav</value>
		</property>
		<property name="frequencyInKHz">
			<value>44.0999985</value>
		</property>
		<property name="channelCount">
			<value>2</value>
		</property>
		<property name="length">
			<value>0.79145124716553283</value>
		</property>
		<relationship name="masterAssetFolder">
			<destination>{458742aa-51b5-40ce-b4e7-5d3674fc37e6}</destination>
		</relationship>
	</object>
</objects>
